LICENSE
README.md
setup.py
quantylab/rltrader/__init__.py
quantylab/rltrader/agent.py
quantylab/rltrader/data_manager.py
quantylab/rltrader/environment.py
quantylab/rltrader/learners.py
quantylab/rltrader/settings.py
quantylab/rltrader/utils.py
quantylab/rltrader/visualizer.py
quantylab/rltrader/networks/__init__.py
quantylab/rltrader/networks/networks_keras.py
quantylab/rltrader/networks/networks_pytorch.py
rltrader.egg-info/PKG-INFO
rltrader.egg-info/SOURCES.txt
rltrader.egg-info/dependency_links.txt
rltrader.egg-info/top_level.txt