Metadata-Version: 2.1
Name: rltrader
Version: 3.0
Summary: Quantylab Reinforcement Learning for Stock Trading
Home-page: https://github.com/quantylab/rltrader
Author: Quantylab
Author-email: quantylab@gmail.com
License: UNKNOWN
Platform: UNKNOWN
License-File: LICENSE
